fast_mtx_reader.py
fast_mtx_reader-0.5.0.dist-info/METADATA
fast_mtx_reader-0.5.0.dist-info/WHEEL
fast_mtx_reader-0.5.0.dist-info/licenses/LICENSE
fast_mtx_reader-0.5.0.dist-info/RECORD
