Metadata-Version: 2.4
Name: fast_mtx_reader
Version: 0.5.0
Summary: 给脑图谱平台自用的批量 mtx 读取器，包含内部格式的数据集格式解析
License-File: LICENSE
Requires-Python: >=3.10
Requires-Dist: anndata
Requires-Dist: fastexcel
Requires-Dist: numpy
Requires-Dist: pandas>=2
Requires-Dist: polars>=1
Requires-Dist: scipy>=1
Requires-Dist: tqdm
